airflow/providers/hive_zk/provider.yaml
airflow/providers/hive_zk/hooks/hive.py
airflow_providers_hive_zk-0.0.1.dist-info/LICENSE
airflow_providers_hive_zk-0.0.1.dist-info/METADATA
airflow_providers_hive_zk-0.0.1.dist-info/WHEEL
airflow_providers_hive_zk-0.0.1.dist-info/top_level.txt
airflow_providers_hive_zk-0.0.1.dist-info/RECORD
