Metadata-Version: 2.1
Name: airflow-providers-hive-zk
Version: 0.0.1
Summary: Hive hook for Airflow using Zookeeper discovery service
Home-page: https://github.com/SVESoftware/airflow-providers-hive-zk
Author: Drazen Nezic
Author-email: info@trialogic.hr
Project-URL: Bug Tracker, https://github.com/SVESoftware/airflow-providers-hive-zk/issues
Classifier: Programming Language :: Python :: 3
Classifier: License :: OSI Approved :: MIT License
Classifier: Operating System :: OS Independent
Requires-Python: >=3.8
License-File: LICENSE
